MANIFEST.in
README.rst
setup.cfg
setup.py
Office365Api_27.egg-info/PKG-INFO
Office365Api_27.egg-info/SOURCES.txt
Office365Api_27.egg-info/dependency_links.txt
Office365Api_27.egg-info/requires.txt
Office365Api_27.egg-info/top_level.txt
office365api/__init__.py
office365api/connection.py
office365api/mail/__init__.py
office365api/mail/base.py
office365api/mail/drafts.py
office365api/mail/folder.py
office365api/mail/inbox.py
office365api/mail/mail.py
office365api/model/__init__.py
office365api/model/model.py
office365api/mail/__init__.py
office365api/mail/base.py
office365api/mail/drafts.py
office365api/mail/folder.py
office365api/mail/inbox.py
office365api/mail/mail.py
office365api/model/__init__.py
office365api/model/model.py