Metadata-Version: 1.1
Name: Office365Api-27
Version: 0.0.6
Summary: Python library for working with Microsoft Office 365
Home-page: https://github.com/swimlane/python-office365
Author: Dmitriy Krasnikov
Author-email: dmitriy.krasnikov@swimlane.com
License: MIT
Platform: UNKNOWN
Classifier: Development Status :: 4 - Beta
Classifier: Intended Audience :: Developers
Classifier: License :: OSI Approved :: MIT License
Classifier: Operating System :: OS Independent
Classifier: Programming Language :: Python
Classifier: Programming Language :: Python :: 3.5
Classifier: Programming Language :: Python :: Implementation :: PyPy
Classifier: Topic :: Software Development :: Libraries :: Python Modules
Classifier: Topic :: Office/Business :: Office Suites
Classifier: Topic :: Software Development :: Libraries
